MANIFEST.in
README.rst
setup.py
backupmanager/__init__.py
backupmanager/__main__.py
backupmanager/backup.yml.dist
backupmanager/common.py
backupmanager.egg-info/PKG-INFO
backupmanager.egg-info/SOURCES.txt
backupmanager.egg-info/dependency_links.txt
backupmanager.egg-info/entry_points.txt
backupmanager.egg-info/requires.txt
backupmanager.egg-info/top_level.txt
backupmanager/systemd/backup.service
backupmanager/systemd/backup.timer
backupmanager/tools/__init__.py
backupmanager/tools/borg.py