Metadata-Version: 1.1
Name: backupmanager
Version: 0.2.9
Summary: A wrapper to unify configuration/running backup tools
Home-page: https://github.com/MartijnBraam/backupmanager
Author: Martijn Braam
Author-email: martijn@brixit.nl
License: MIT
Keywords: backup,linux,manager
Platform: UNKNOWN
Classifier: Programming Language :: Python
Classifier: Programming Language :: Python :: 3
Classifier: Development Status :: 4 - Beta
Classifier: Operating System :: POSIX :: Linux
Classifier: License :: OSI Approved :: MIT License
